docker_help/__init__.py
docker_help/dockerModulo.py
docker_help-0.0.3.dist-info/METADATA
docker_help-0.0.3.dist-info/WHEEL
docker_help-0.0.3.dist-info/top_level.txt
docker_help-0.0.3.dist-info/RECORD
