Metadata-Version: 2.1
Name: docker-help
Version: 0.0.3
Summary: Pacote para manipular o docker 
Home-page: https://github.com/ggbr/docker-help
Author: Gabriel Sousa dos Santos
Author-email: ggbr12.neg@gmail.com
License: UNKNOWN
Platform: UNKNOWN
Classifier: Programming Language :: Python :: 3
Classifier: License :: OSI Approved :: MIT License
Classifier: Operating System :: OS Independent
